qageneratorllm/__init__.py
qageneratorllm/generator.py
qageneratorllm/loader.py
qageneratorllm/qa_dataclass.py
qageneratorllm/prompts/__init__.py
qageneratorllm/prompts/mcq_prompt.py
qageneratorllm/prompts/qa_prompt.py
qageneratorllm-0.1.3.dist-info/METADATA
qageneratorllm-0.1.3.dist-info/WHEEL
qageneratorllm-0.1.3.dist-info/entry_points.txt
qageneratorllm-0.1.3.dist-info/licenses/LICENSE
qageneratorllm-0.1.3.dist-info/RECORD
