Metadata-Version: 2.4
Name: qageneratorllm
Version: 0.1.3
Summary: A Python package for generating educational questions and answers using various LLM providers.
Project-URL: Homepage, https://github.com/KameniAlexNea/create-dataset
Project-URL: Repository, https://github.com/KameniAlexNea/create-dataset
Project-URL: Bug Tracker, https://github.com/KameniAlexNea/create-dataset/issues
Author-email: Alex Kameni <kamenialexnea@gmail.com>
License: MIT
License-File: LICENSE
Keywords: ai,education,llm,mcq,questions,quiz
Classifier: Intended Audience :: Education
Classifier: License :: OSI Approved :: MIT License
Classifier: Operating System :: OS Independent
Classifier: Programming Language :: Python :: 3
Classifier: Programming Language :: Python :: 3.10
Classifier: Programming Language :: Python :: 3.11
Classifier: Topic :: Education
Classifier: Topic :: Scientific/Engineering :: Artificial Intelligence
Requires-Python: <4.0,>=3.10
Requires-Dist: langchain
Requires-Dist: langchain-anthropic
Requires-Dist: langchain-groq>=0.3.2
Requires-Dist: langchain-ollama
Requires-Dist: langchain-openai
Requires-Dist: langchain-xai
Requires-Dist: llm-output-parser
Requires-Dist: node-chunker
Requires-Dist: pydantic
Provides-Extra: dev
Requires-Dist: black<25.0,>=23.0; extra == 'dev'
Requires-Dist: build; extra == 'dev'
Requires-Dist: codespell>=2.2.0; extra == 'dev'
Requires-Dist: coverage>=5.0; extra == 'dev'
Requires-Dist: gradio>=5.30.0; extra == 'dev'
Requires-Dist: mypy>=1.0; extra == 'dev'
Requires-Dist: pickleshare; extra == 'dev'
Requires-Dist: pre-commit>=3.0; extra == 'dev'
Requires-Dist: ruff>=0.1.0; extra == 'dev'
Requires-Dist: safety; extra == 'dev'
Requires-Dist: sphinx; extra == 'dev'
Requires-Dist: tox; extra == 'dev'
Requires-Dist: twine; extra == 'dev'
Requires-Dist: wheel; extra == 'dev'
Provides-Extra: test
Requires-Dist: pytest-cov>=4.0; extra == 'test'
Requires-Dist: pytest-mock>=3.10; extra == 'test'
Requires-Dist: pytest>=8.0; extra == 'test'
